Metadata-Version: 2.1
Name: tt-sketch
Version: 1.1
Summary: Streaming randomized TT-decompositions for structured tensors.
Home-page: https://github.com/RikVoorhaar/tt-sketch
Author: Rik Voorhaar
Keywords: mathematics machine-learning tensors linear-algebra
Classifier: Development Status :: 5 - Production/Stable
Classifier: License :: OSI Approved :: Apache Software License
Classifier: Operating System :: OS Independent
Classifier: Intended Audience :: Science/Research
Classifier: Programming Language :: Python :: 3
Classifier: Topic :: Scientific/Engineering :: Mathematics
Classifier: Topic :: Scientific/Engineering :: Artificial Intelligence
